MANIFEST.in
setup.cfg
setup.py
toned/__init__.py
toned/finder.py
toned.egg-info/PKG-INFO
toned.egg-info/SOURCES.txt
toned.egg-info/dependency_links.txt
toned.egg-info/not-zip-safe
toned.egg-info/top_level.txt