Metadata-Version: 1.1
Name: toned
Version: 1.0.0
Summary: a tool to allow boolean search operations on files
Home-page: https://github.com/kouroshparsa/toned
Author: Kourosh Parsa
Author-email: kouroshtheking@gmail.com
License: GNU
Download-URL: https://github.com/kouroshparsa/toned/packages/1.0.0
Platform: UNKNOWN
Classifier: Development Status :: 5 - Production/Stable
Classifier: Intended Audience :: Developers
Classifier: Operating System :: OS Independent
Classifier: Programming Language :: Python
Classifier: Programming Language :: Python :: 2
Classifier: Programming Language :: Python :: 2.6
Classifier: Programming Language :: Python :: 2.7
Classifier: Programming Language :: Python :: 3
Classifier: Programming Language :: Python :: 3.3
Classifier: Programming Language :: Python :: 3.4
Classifier: Programming Language :: Python :: 3.5
